LICENSE
MANIFEST.in
README.rst
requirements.txt
setup.cfg
setup.py
dummyserial/__init__.py
dummyserial/classes.py
dummyserial/constants.py
dummyserial/exceptions.py
dummyserial.egg-info/PKG-INFO
dummyserial.egg-info/SOURCES.txt
dummyserial.egg-info/dependency_links.txt
dummyserial.egg-info/not-zip-safe
dummyserial.egg-info/pbr.json
dummyserial.egg-info/requires.txt
dummyserial.egg-info/top_level.txt