Metadata-Version: 1.0
Name: dummyserial
Version: 1.0.0
Summary: Dummy Serial Implementation.
Home-page: https://github.com/ampledata/dummyserial
Author: Greg Albrecht
Author-email: gba@orionlabs.io
License: Copyright 2016 Orion Labs, Inc.
